transip_dns/__init__.py
transip_dns/accesstoken.py
transip_dns/env_params.py
transip_dns/transip_dns.py
transip_dns/transip_interface.py
transip_dns-1.0.0.dist-info/LICENSE
transip_dns-1.0.0.dist-info/METADATA
transip_dns-1.0.0.dist-info/WHEEL
transip_dns-1.0.0.dist-info/entry_points.txt
transip_dns-1.0.0.dist-info/top_level.txt
transip_dns-1.0.0.dist-info/RECORD
