Metadata-Version: 2.1
Name: transip-dns
Version: 1.0.0
Summary: TransIP Dns record management script
Home-page: https://github.com/bheuvel/transip_dns
Author: Bob
Author-email: bob.github@heuvel.nu
License: MIT
Project-URL: Source, https://github.com/bheuvel/transip_dns
Project-URL: Tracker, https://github.com/bheuvel/transip_dns/issues
Keywords: dns transip ddns
Platform: UNKNOWN
Classifier: Development Status :: 5 - Production/Stable
Classifier: Intended Audience :: Developers
Classifier: Intended Audience :: System Administrators
Classifier: License :: OSI Approved :: MIT License
Classifier: Natural Language :: English
Classifier: Operating System :: OS Independent
Classifier: Programming Language :: Python
Classifier: Programming Language :: Python :: 3.6
Classifier: Programming Language :: Python :: 3.7
Classifier: Programming Language :: Python :: 3.8
Classifier: Programming Language :: Python :: 3.9
Classifier: Programming Language :: Python :: 3.10
Classifier: Topic :: Internet :: Name Service (DNS)
Classifier: Topic :: Utilities
Requires-Python: >=3.6
Requires-Dist: cryptography
Requires-Dist: requests
